{
  "version": "7",
  "dialect": "postgresql",
  "entries": [
    {
      "idx": 0,
      "version": "7",
      "when": 1771635528982,
      "tag": "0000_shiny_hedge_knight",
      "breakpoints": true
    },
    {
      "idx": 1,
      "version": "7",
      "when": 1771635907212,
      "tag": "0001_calm_juggernaut",
      "breakpoints": true
    },
    {
      "idx": 2,
      "version": "7",
      "when": 1771801950913,
      "tag": "0002_lonely_lilith",
      "breakpoints": true
    },
    {
      "idx": 3,
      "version": "7",
      "when": 1771802124005,
      "tag": "0003_spotty_lockjaw",
      "breakpoints": true
    },
    {
      "idx": 4,
      "version": "7",
      "when": 1771802711077,
      "tag": "0004_empty_wind_dancer",
      "breakpoints": true
    },
    {
      "idx": 5,
      "version": "7",
      "when": 1772048263191,
      "tag": "0005_cynical_gunslinger",
      "breakpoints": true
    },
    {
      "idx": 6,
      "version": "7",
      "when": 1773487661706,
      "tag": "0006_talented_susan_delgado",
      "breakpoints": true
    }
  ]
}